[
  {
    "Event": "Women's 50m Freestyle",
    "Pool": "LCM",
    "Record Description": "",
    "Record": "",
    "Time": "24.17",
    "Athlete": "CURZAN Claire",
    "NF Code": "USA",
    "Gender": "W",
    "Competition": "TAC Spring Invitational 2021 (50m)",
    "Country": "United States of America",
    "City": "Cary",
    "Date": "14-May-21",
    "Splits": "",
    "Tags": "",
    "Status": ""
  },
  {
    "Event": "Women's 100m Freestyle",
    "Pool": "LCM",
    "Record Description": "",
    "Record": "",
    "Time": "52.70",
    "Athlete": "OLEKSIAK Penny",
    "NF Code": "CAN",
    "Gender": "W",
    "Competition": "Olympic Games Rio 2016",
    "Country": "Brazil",
    "City": "Rio de Janeiro",
    "Date": "11-Aug-16",
    "Splits": "25.70, 52.70",
    "Tags": "",
    "Status": ""
  },
  {
    "Event": "Women's 200m Freestyle",
    "Pool": "LCM",
    "Record Description": "",
    "Record": "",
    "Time": "01:53.65",
    "Athlete": "MCINTOSH Summer",
    "NF Code": "CAN",
    "Gender": "W",
    "Competition": "World Aquatics Championships - Fukuoka 2023",
    "Country": "Japan",
    "City": "Fukuoka",
    "Date": "26-Jul-23",
    "Splits": "27.03, 55.82, 01:24.77, 01:53.65",
    "Tags": "",
    "Status": ""
  },
  {
    "Event": "Women's 400m Freestyle",
    "Pool": "LCM",
    "Record Description": "",
    "Record": "",
    "Time": "03:56.08",
    "Athlete": "MCINTOSH Summer",
    "NF Code": "CAN",
    "Gender": "W",
    "Competition": "2023 BELL Canadian Trials",
    "Country": "Canada",
    "City": "Toronto",
    "Date": "28-Mar-23",
    "Splits": "27.34, 56.46, 01:26.11, 01:55.91, 02:25.56, 02:55.84, 03:26.10, 03:56.08",
    "Tags": "",
    "Status": ""
  },
  {
    "Event": "Women's 800m Freestyle",
    "Pool": "LCM",
    "Record Description": "",
    "Record": "",
    "Time": "08:11.00",
    "Athlete": "LEDECKY Katie",
    "NF Code": "USA",
    "Gender": "W",
    "Competition": "15th FINA World Championships",
    "Country": "Spain",
    "City": "Barcelona",
    "Date": "22-Jun-13",
    "Splits": "28.34, 58.74, 01:29.56, 02:00.22, 02:30.98, 03:01.88, 03:32.74, 04:03.55, 04:34.40, 05:05.41, 05:36.46, 06:07.69, 06:38.92, 07:10.13, 07:41.11, 08:11.00",
    "Tags": "",
    "Status": ""
  },
  {
    "Event": "Women's 1500m Freestyle",
    "Pool": "LCM",
    "Record Description": "",
    "Record": "",
    "Time": "15:28.36",
    "Athlete": "LEDECKY Katie",
    "NF Code": "USA",
    "Gender": "W",
    "Competition": "Pan Pacific Swimming Championships 2014",
    "Country": "Australia",
    "City": "Gold Coast",
    "Date": "24-Aug-14",
    "Splits": "28.25, 58.26, 01:28.91, 01:59.39, 02:30.22, 03:00.86, 03:31.78, 04:02.47, 04:33.40, 05:04.28, 05:35.40, 06:06.33, 06:37.46, 07:08.57, 07:39.73, 08:10.67, 08:41.87, 09:12.87, 09:44.13, 10:15.16, 10:46.40, 11:17.51, 11:48.80, 12:20.10, 12:51.35, 13:22.58, 13:54.12, 14:25.59, 14:57.19, 15:28.36",
    "Tags": "",
    "Status": ""
  },
  {
    "Event": "Women's 50m Backstroke",
    "Pool": "LCM",
    "Record Description": "",
    "Record": "",
    "Time": "27.49",
    "Athlete": "ATHERTON Minna",
    "NF Code": "AUS",
    "Gender": "W",
    "Competition": "Brisbane Aquatic Championship 2016",
    "Country": "Australia",
    "City": "Brisbane",
    "Date": "07-Feb-16",
    "Splits": "27.49",
    "Tags": "",
    "Status": ""
  },
  {
    "Event": "Women's 100m Backstroke",
    "Pool": "LCM",
    "Record Description": "",
    "Record": "",
    "Time": "57.57",
    "Athlete": "SMITH Regan",
    "NF Code": "USA",
    "Gender": "W",
    "Competition": "18th FINA World Championships 2019",
    "Country": "Korea",
    "City": "Gwangju",
    "Date": "28-Jul-19",
    "Splits": "27.74, 57.57",
    "Tags": "",
    "Status": ""
  },
  {
    "Event": "Women's 200m Backstroke",
    "Pool": "LCM",
    "Record Description": "",
    "Record": "",
    "Time": "02:03.35",
    "Athlete": "SMITH Regan",
    "NF Code": "USA",
    "Gender": "W",
    "Competition": "18th FINA World Championships 2019",
    "Country": "Korea",
    "City": "Gwangju",
    "Date": "26-Jul-19",
    "Splits": "29.06, 01:00.22, 01:31.78, 02:03.35",
    "Tags": "",
    "Status": ""
  },
  {
    "Event": "Women's 50m Breaststroke",
    "Pool": "LCM",
    "Record Description": "",
    "Record": "",
    "Time": "29.30",
    "Athlete": "PILATO Benedetta",
    "NF Code": "ITA",
    "Gender": "W",
    "Competition": "35th European Swimming Championships 2021",
    "Country": "Hungary",
    "City": "Budapest",
    "Date": "22-May-21",
    "Splits": "29.30",
    "Tags": "",
    "Status": ""
  },
  {
    "Event": "Women's 100m Breaststroke",
    "Pool": "LCM",
    "Record Description": "",
    "Record": "",
    "Time": "01:04.35",
    "Athlete": "MEILUTYTE Ruta",
    "NF Code": "LTU",
    "Gender": "W",
    "Competition": "15th FINA World Championships",
    "Country": "Spain",
    "City": "Barcelona",
    "Date": "29-Jul-13",
    "Splits": "29.97, 01:04.35",
    "Tags": "",
    "Status": ""
  },
  {
    "Event": "Women's 200m Breaststroke",
    "Pool": "LCM",
    "Record Description": "",
    "Record": "",
    "Time": "02:19.64",
    "Athlete": "GUNES Viktoria Zeynep",
    "NF Code": "TUR",
    "Gender": "W",
    "Competition": "5th FINA World Junior Swimming Championships 2015",
    "Country": "Singapore",
    "City": "Singapore",
    "Date": "30-Aug-15",
    "Splits": "32.10, 01:07.56, 01:43.35, 02:19.64",
    "Tags": "",
    "Status": ""
  },
  {
    "Event": "Women's 50m Butterfly",
    "Pool": "LCM",
    "Record Description": "",
    "Record": "",
    "Time": "25.46",
    "Athlete": "IKEE Rikako",
    "NF Code": "JPN",
    "Gender": "W",
    "Competition": "41st Japan JOC Junior Olympic Cup Summer 2018",
    "Country": "Japan",
    "City": "Tokyo",
    "Date": "26-Aug-18",
    "Splits": "25.46",
    "Tags": "",
    "Status": ""
  },
  {
    "Event": "Women's 100m Butterfly",
    "Pool": "LCM",
    "Record Description": "",
    "Record": "",
    "Time": "56.33",
    "Athlete": "HIRAI Mizuki",
    "NF Code": "JPN",
    "Gender": "W",
    "Competition": "62nd Kanagawa High School Swim Meet",
    "Country": "Japan",
    "City": "Yokohama",
    "Date": "22-Jun-24",
    "Splits": "26.26, 56.33",
    "Tags": "",
    "Status": ""
  },
  {
    "Event": "Women's 200m Butterfly",
    "Pool": "LCM",
    "Record Description": "",
    "Record": "",
    "Time": "02:03.03",
    "Athlete": "MCINTOSH Summer",
    "NF Code": "CAN",
    "Gender": "W",
    "Competition": "Olympic Games Paris 2024",
    "Country": "France",
    "City": "Paris",
    "Date": "01-Aug-24",
    "Splits": "27.38, 58.97, 01:30.70, 02:03.03",
    "Tags": "",
    "Status": ""
  },
  {
    "Event": "Women's 200m Medley",
    "Pool": "LCM",
    "Record Description": "",
    "Record": "",
    "Time": "02:06.56",
    "Athlete": "MCINTOSH Summer",
    "NF Code": "CAN",
    "Gender": "W",
    "Competition": "Olympic Games Paris 2024",
    "Country": "France",
    "City": "Paris",
    "Date": "03-Aug-24",
    "Splits": "26.80, 58.60, 01:36.13, 02:06.56",
    "Tags": "",
    "Status": ""
  },
  {
    "Event": "Women's 400m Medley",
    "Pool": "LCM",
    "Record Description": "",
    "Record": "",
    "Time": "04:24.38",
    "Athlete": "MCINTOSH Summer",
    "NF Code": "CAN",
    "Gender": "W",
    "Competition": "2024 Bell Canadian Trials",
    "Country": "Canada",
    "City": "Toronto",
    "Date": "16-May-24",
    "Splits": "27.55, 59.18, 01:33.31, 02:06.30, 02:44.22, 03:23.43, 03:54.66, 04:24.38",
    "Tags": "",
    "Status": ""
  },
  {
    "Event": "Women's 4x100m Freestyle Relay",
    "Pool": "LCM",
    "Record Description": "",
    "Record": "",
    "Time": "03:36.19",
    "Athlete": "TORRI HUSKE, GRETCHEN WALSH, CHARLOTTE CRUSH, ERIN GEMMELL",
    "NF Code": "USA",
    "Gender": "W",
    "Competition": "7th FINA World Junior Swimming Championships 2019",
    "Country": "Hungary",
    "City": "Budapest",
    "Date": "20-Aug-19",
    "Splits": "26.15, 54.34, 01:20.10, 01:48.33, 02:14.22, 02:42.53, 03:07.96, 03:36.19",
    "Tags": "",
    "Status": ""
  },
  {
    "Event": "Women's 4x200m Freestyle Relay",
    "Pool": "LCM",
    "Record Description": "",
    "Record": "",
    "Time": "03:36.19",
    "Athlete": "TORRI HUSKE, GRETCHEN WALSH, CHARLOTTE CRUSH, ERIN GEMMELL",
    "NF Code": "USA",
    "Gender": "W",
    "Competition": "7th FINA World Junior Swimming Championships 2019",
    "Country": "Hungary",
    "City": "Budapest",
    "Date": "20-Aug-19",
    "Splits": "26.15, 54.34, 01:20.10, 01:48.33, 02:14.22, 02:42.53, 03:07.96, 03:36.19",
    "Tags": "",
    "Status": ""
  },
  {
    "Event": "Women's 4x100m Medley Relay",
    "Pool": "LCM",
    "Record Description": "",
    "Record": "",
    "Time": "03:36.19",
    "Athlete": "TORRI HUSKE, GRETCHEN WALSH, CHARLOTTE CRUSH, ERIN GEMMELL",
    "NF Code": "USA",
    "Gender": "W",
    "Competition": "7th FINA World Junior Swimming Championships 2019",
    "Country": "Hungary",
    "City": "Budapest",
    "Date": "20-Aug-19",
    "Splits": "26.15, 54.34, 01:20.10, 01:48.33, 02:14.22, 02:42.53, 03:07.96, 03:36.19",
    "Tags": "",
    "Status": ""
  }
]